Workbook
Name AUD: #REF!
Name AUD: #REF!
Name AUD: #REF!
Name CAD: #REF!
Name CAD: #REF!
Name CAD: #REF!
Name Capital_raise: [1]inputs!$K$6
Name col: #REF!
Name col: #REF!
Name col: #REF!
Name ddd: Word
Name ddd: Word
Name ddd: Word
Name dealprice: #REF!
Name dealprice: #REF!
Name dealprice: #REF!
Name DocType: Word
Name DocType: Word
Name DocType: Word
Name EUR: #REF!
Name EUR: #REF!
Name EUR: #REF!
Name fff: Word
Name fff: Word
Name fff: Word
Name GBP: #REF!
Name GBP: #REF!
Name GBP: #REF!
Name gg: Word
Name gg: Word
Name gg: Word
Name HKD: #REF!
Name HKD: #REF!
Name HKD: #REF!
Name MonitorCol: 1
Name MonitorRow: 1
Name MonthNames: {"Jan","Feb","Mar","Apr","May","Jun","Jul","Aug","Sep","Oct","Nov","Dec";"January","February","March","April","May","June","July","August","September","October","November","December"}
Name pbFileName: MID(CELL("filename"),FIND("[",CELL("FILENAME"))+1,(FIND("]",CELL("FILENAME"))) - (FIND("[",CELL("FILENAME"))+1))
Name pbPrinterFormat: "\\SGB24831\P0047496 on Ne05:"
Name pbStartPageNumber: 1
Name pbUpdatePageNumbering: TRUE
Name row: #REF!
Name row: #REF!
Name row: #REF!
Name SEK: #REF!
Name SEK: #REF!
Name SEK: #REF!
Name SGD: #REF!
Name SGD: #REF!
Name SGD: #REF!
Name ticker: #REF!
Name ticker: #REF!
Name ticker: #REF!
Name TickerCell: #REF!
Name TickerCell: #REF!
Name TickerCell: #REF!

Sheet model
B1: Standard Operating Model
B3: Period | E3: 41274 | F3: 41639 | G3: 42004 | H3: 42369 | I3: 42735 | J3: 43100 | K3: 43465 | L3: 43830 | M3: 44196 | N3: 44561 | O3: 44926 | P3: 45291
B5: ASSUMPTIONS
A6: X
E8: =E$3 -> 41274 | F8: =F$3 -> 41639 | G8: =G$3 -> 42004 | H8: =H$3 -> 42369 | I8: =I$3 -> 42735 | J8: =J$3 -> 43100 | K8: =K$3 -> 43465 | L8: =L$3 -> 43830 | ... P8: =P$3 -> 45291
B10: Loans
B11: New Volume | F11: 400 | G11: =F11 -> 400 | H11: =G11 -> 400 | I11: =H11 -> 400 | J11: =I11 -> 400 | K11: =J11 -> 400 | L11: =K11 -> 400 | M11: =L11 -> 400 | N11: =M11 -> 400 | ... P11: =O11 -> 400
B12: Amortization/Prepayment | F12: 0.2 | G12: =F12 -> 0.2 | H12: =G12 -> 0.2 | I12: =H12 -> 0.2 | J12: =I12 -> 0.2 | K12: =J12 -> 0.2 | L12: =K12 -> 0.2 | M12: =L12 -> 0.2 | N12: =M12 -> 0.2 | ... P12: =O12 -> 0.2
B13: Net Charge-Offs | F13: 0.01 | G13: =F13 -> 0.01 | H13: =G13 -> 0.01 | I13: =H13 -> 0.01 | J13: =I13 -> 0.01 | K13: =J13 -> 0.01 | L13: =K13 -> 0.01 | M13: =L13 -> 0.01 | N13: =M13 -> 0.01 | ... P13: =O13 -> 0.01
B14: Loan Yield | F14: 0.055 | G14: =F14 -> 0.055 | H14: =G14 -> 0.055 | I14: =H14 -> 0.055 | J14: =I14 -> 0.055 | K14: =J14 -> 0.055 | L14: =K14 -> 0.055 | M14: =L14 -> 0.055 | N14: =M14 -> 0.055 | ... P14: =O14 -> 0.055
B15: Roll-Forward:
B16: BOP Balance | F16: =E92 -> 1350 | G16: =F20 -> 1466.5 | H16: =G20 -> 1558.535 | I16: =H20 -> 1631.2426 | J16: =I20 -> 1688.6817 | K16: =J20 -> 1734.0585 | L16: =K20 -> 1769.9062 | M16: =L20 -> 1798.2259 | N16: =M20 -> 1820.5985 | ... P16: =O20 -> 1852.2355
B17: Originations | F17: =F11 -> 400 | G17: =G11 -> 400 | H17: =H11 -> 400 | I17: =I11 -> 400 | J17: =J11 -> 400 | K17: =K11 -> 400 | L17: =L11 -> 400 | M17: =M11 -> 400 | ... P17: =P11 -> 400
B18: Amortization/Prepayment | F18: =-F16*F12 -> -270 | G18: =-G16*G12 -> -293.3 | H18: =-H16*H12 -> -311.707 | I18: =-I16*I12 -> -326.24853 | J18: =-J16*J12 -> -337.73634 | K18: =-K16*K12 -> -346.81171 | L18: =-L16*L12 -> -353.98125 | M18: =-M16*M12 -> -359.64519 | ... P18: =-P16*P12 -> -370.4471
B19: Net-Charge Offs | F19: =-F16*F13 -> -13.5 | G19: =-G16*G13 -> -14.665 | H19: =-H16*H13 -> -15.58535 | I19: =-I16*I13 -> -16.312427 | J19: =-J16*J13 -> -16.886817 | K19: =-K16*K13 -> -17.340585 | L19: =-L16*L13 -> -17.699062 | M19: =-M16*M13 -> -17.982259 | ... P19: =-P16*P13 -> -18.522355
B20: EOP Balance | F20: =SUM(F16:F19) -> 1466.5 | G20: =SUM(G16:G19) -> 1558.535 | H20: =SUM(H16:H19) -> 1631.2426 | I20: =SUM(I16:I19) -> 1688.6817 | J20: =SUM(J16:J19) -> 1734.0585 | K20: =SUM(K16:K19) -> 1769.9062 | L20: =SUM(L16:L19) -> 1798.2259 | M20: =SUM(M16:M19) -> 1820.5985 | ... P20: =SUM(P16:P19) -> 1863.2661
B21: Average Balance | F21: =AVERAGE(F20,F16) -> 1408.25 | G21: =AVERAGE(G20,G16) -> 1512.5175 | H21: =AVERAGE(H20,H16) -> 1594.8888 | I21: =AVERAGE(I20,I16) -> 1659.9622 | J21: =AVERAGE(J20,J16) -> 1711.3701 | K21: =AVERAGE(K20,K16) -> 1751.9824 | L21: =AVERAGE(L20,L16) -> 1784.0661 | M21: =AVERAGE(M20,M16) -> 1809.4122 | ... P21: =AVERAGE(P20,P16) -> 1857.7508
B22: Interest Income | F22: =F21*F14 -> 77.45375 | G22: =G21*G14 -> 83.188462 | H22: =H21*H14 -> 87.718885 | I22: =I21*I14 -> 91.297919 | J22: =J21*J14 -> 94.125356 | K22: =K21*K14 -> 96.359032 | L22: =L21*L14 -> 98.123635 | M22: =M21*M14 -> 99.517672 | ... P22: =P21*P14 -> 102.17629
B24: Securities and Cash
B25: Securities as % of Assets | E25: =E27/E100 -> 0.16620499 | F25: 0.2 | G25: =F25 -> 0.2 | H25: =G25 -> 0.2 | I25: =H25 -> 0.2 | J25: =I25 -> 0.2 | K25: =J25 -> 0.2 | L25: =K25 -> 0.2 | M25: =L25 -> 0.2 | N25: =M25 -> 0.2 | ... P25: =O25 -> 0.2
B26: Securities Yield | E26: Opening | F26: 0.03 | G26: =F26 -> 0.03 | H26: =G26 -> 0.03 | I26: =H26 -> 0.03 | J26: =I26 -> 0.03 | K26: =J26 -> 0.03 | L26: =K26 -> 0.03 | M26: =L26 -> 0.03 | N26: =M26 -> 0.03 | ... P26: =O26 -> 0.03
B27: Securities Balance | E27: =E91 -> 300 | F27: =F91 -> 405.75063 | G27: =G91 -> 429.30674 | H27: =H91 -> 448.12135 | I27: =I91 -> 463.19427 | J27: =J91 -> 475.31545 | K27: =K91 -> 485.10902 | L27: =L91 -> 493.06813 | ... P27: =P91 -> 513.22689
B28: Average Balance | F28: =AVERAGE(E27:F27) -> 352.87531 | G28: =AVERAGE(F27:G27) -> 417.52868 | H28: =AVERAGE(G27:H27) -> 438.71405 | I28: =AVERAGE(H27:I27) -> 455.65781 | J28: =AVERAGE(I27:J27) -> 469.25486 | K28: =AVERAGE(J27:K27) -> 480.21223 | L28: =AVERAGE(K27:L27) -> 489.08858 | M28: =AVERAGE(L27:M27) -> 496.3253 | ... P28: =AVERAGE(O27:P27) -> 511.33545
B29: Interest Income | F29: =F26*F28 -> 10.586259 | G29: =G26*G28 -> 12.525861 | H29: =H26*H28 -> 13.161421 | I29: =I26*I28 -> 13.669734 | J29: =J26*J28 -> 14.077646 | K29: =K26*K28 -> 14.406367 | L29: =L26*L28 -> 14.672657 | M29: =M26*M28 -> 14.889759 | ... P29: =P26*P28 -> 15.340063
B31: Cash Yield | E31: Opening | F31: 0.0025 | G31: =F31 -> 0.0025 | H31: =G31 -> 0.0025 | I31: =H31 -> 0.0025 | J31: =I31 -> 0.0025 | K31: =J31 -> 0.0025 | L31: =K31 -> 0.0025 | M31: =L31 -> 0.0025 | N31: =M31 -> 0.0025 | ... P31: =O31 -> 0.0025
B32: Securities Balance | E32: =E90 -> 75 | F32: =F90 -> 76.5 | G32: =G90 -> 78.03 | H32: =H90 -> 79.5906 | I32: =I90 -> 81.182412 | J32: =J90 -> 82.80606 | K32: =K90 -> 84.462181 | L32: =L90 -> 86.151425 | ... P32: =P90 -> 93.253073
B33: Average Balance | F33: =AVERAGE(E32:F32) -> 75.75 | G33: =AVERAGE(F32:G32) -> 77.265 | H33: =AVERAGE(G32:H32) -> 78.8103 | I33: =AVERAGE(H32:I32) -> 80.386506 | J33: =AVERAGE(I32:J32) -> 81.994236 | K33: =AVERAGE(J32:K32) -> 83.634121 | L33: =AVERAGE(K32:L32) -> 85.306803 | M33: =AVERAGE(L32:M32) -> 87.012939 | ... P33: =AVERAGE(O32:P32) -> 92.338827
B34: Interest Income | F34: =F31*F33 -> 0.189375 | G34: =G31*G33 -> 0.1931625 | H34: =H31*H33 -> 0.19702575 | I34: =I31*I33 -> 0.20096627 | J34: =J31*J33 -> 0.20498559 | K34: =K31*K33 -> 0.2090853 | L34: =L31*L33 -> 0.21326701 | M34: =M31*M33 -> 0.21753235 | ... P34: =P31*P33 -> 0.23084707
B36: Loan Loss Reserve
B37: Reserve/Loans | F37: 0.015 | G37: =F37 -> 0.015 | H37: =G37 -> 0.015 | I37: =H37 -> 0.015 | J37: =I37 -> 0.015 | K37: =J37 -> 0.015 | L37: =K37 -> 0.015 | M37: =L37 -> 0.015 | N37: =M37 -> 0.015 | ... P37: =O37 -> 0.015
B38: Roll-Forward:
B39: BOP Balance | F39: =E93 -> 20 | G39: =F42 -> 21.9975 | H39: =G42 -> 23.378025 | I39: =H42 -> 24.46864 | J39: =I42 -> 25.330225 | K39: =J42 -> 26.010878 | L39: =K42 -> 26.548594 | M39: =L42 -> 26.973389 | N39: =M42 -> 27.308977 | ... P39: =O42 -> 27.783533
B40: Loan Loss Provision | F40: =F42-F39-F41 -> 15.4975 | G40: =G42-G39-G41 -> 16.045525 | H40: =H42-H39-H41 -> 16.675965 | I40: =I42-I39-I41 -> 17.174012 | J40: =J42-J39-J41 -> 17.56747 | K40: =K42-K39-K41 -> 17.878301 | L40: =L42-L39-L41 -> 18.123858 | M40: =M42-M39-M41 -> 18.317848 | ... P40: =P42-P39-P41 -> 18.687813
B41: Net Charge-Offs | F41: =F19 -> -13.5 | G41: =G19 -> -14.665 | H41: =H19 -> -15.58535 | I41: =I19 -> -16.312427 | J41: =J19 -> -16.886817 | K41: =K19 -> -17.340585 | L41: =L19 -> -17.699062 | M41: =M19 -> -17.982259 | ... P41: =P19 -> -18.522355
B42: EOP Balance | F42: =F37*F20 -> 21.9975 | G42: =G37*G20 -> 23.378025 | H42: =H37*H20 -> 24.46864 | I42: =I37*I20 -> 25.330225 | J42: =J37*J20 -> 26.010878 | K42: =K37*K20 -> 26.548594 | L42: =L37*L20 -> 26.973389 | M42: =M37*M20 -> 27.308977 | ... P42: =P37*P20 -> 27.948991
A44: X | B44: Funding
B45: Deposit Growth | F45: 0.05 | G45: =F45 -> 0.05 | H45: =G45 -> 0.05 | I45: =H45 -> 0.05 | J45: =I45 -> 0.05 | K45: =J45 -> 0.05 | L45: =K45 -> 0.05 | M45: =L45 -> 0.05 | N45: =M45 -> 0.05 | ... P45: =O45 -> 0.05
B46: Deposit Cost | E46: Opening | F46: 0.005 | G46: =F46 -> 0.005 | H46: =G46 -> 0.005 | I46: =H46 -> 0.005 | J46: =I46 -> 0.005 | K46: =J46 -> 0.005 | L46: =K46 -> 0.005 | M46: =L46 -> 0.005 | N46: =M46 -> 0.005 | ... P46: =O46 -> 0.005
B47: Deposit Balance | E47: =E103 -> 1500 | F47: =E47*(1+F45) -> 1575 | G47: =F47*(1+G45) -> 1653.75 | H47: =G47*(1+H45) -> 1736.4375 | I47: =H47*(1+I45) -> 1823.2594 | J47: =I47*(1+J45) -> 1914.4223 | K47: =J47*(1+K45) -> 2010.1435 | L47: =K47*(1+L45) -> 2110.6506 | M47: =L47*(1+M45) -> 2216.1832 | ... P47: =O47*(1+P45) -> 2565.509
B48: Average Balance | F48: =AVERAGE(E47:F47) -> 1537.5 | G48: =AVERAGE(F47:G47) -> 1614.375 | H48: =AVERAGE(G47:H47) -> 1695.0938 | I48: =AVERAGE(H47:I47) -> 1779.8484 | J48: =AVERAGE(I47:J47) -> 1868.8409 | K48: =AVERAGE(J47:K47) -> 1962.2829 | L48: =AVERAGE(K47:L47) -> 2060.397 | M48: =AVERAGE(L47:M47) -> 2163.4169 | ... P48: =AVERAGE(O47:P47) -> 2504.4255
B49: Interest Expense | F49: =F46*F48 -> 7.6875 | G49: =G46*G48 -> 8.071875 | H49: =H46*H48 -> 8.4754688 | I49: =I46*I48 -> 8.8992422 | J49: =J46*J48 -> 9.3442043 | K49: =K46*K48 -> 9.8114145 | L49: =L46*L48 -> 10.301985 | M49: =M46*M48 -> 10.817084 | ... P49: =P46*P48 -> 12.522127
B51: Borrowing Cost | E51: Opening | F51: 0.01 | G51: =F51 -> 0.01 | H51: =G51 -> 0.01 | I51: =H51 -> 0.01 | J51: =I51 -> 0.01 | K51: =J51 -> 0.01 | L51: =K51 -> 0.01 | M51: =L51 -> 0.01 | N51: =M51 -> 0.01 | ... P51: =O51 -> 0.01
B52: Borrowing Balance | E52: =E104 -> 100 | F52: =F104 -> 234.36567 | G52: =G104 -> 257.73039 | H52: =H104 -> 252.5752 | I52: =I104 -> 223.85105 | J52: =J104 -> 175.41716 | K52: =K104 -> 110.26765 | L52: =L104 -> 30.710491 | ... P52: =P104 -> -402.32861
B53: Average Balance | F53: =AVERAGE(E52:F52) -> 167.18284 | G53: =AVERAGE(F52:G52) -> 246.04803 | H53: =AVERAGE(G52:H52) -> 255.15279 | I53: =AVERAGE(H52:I52) -> 238.21312 | J53: =AVERAGE(I52:J52) -> 199.6341 | K53: =AVERAGE(J52:K52) -> 142.84241 | L53: =AVERAGE(K52:L52) -> 70.489071 | M53: =AVERAGE(L52:M52) -> -15.390405 | ... P53: =AVERAGE(O52:P52) -> -340.59254
B54: Interest Expense | F54: =F51*F53 -> 1.6718284 | G54: =G51*G53 -> 2.4604803 | H54: =H51*H53 -> 2.5515279 | I54: =I51*I53 -> 2.3821312 | J54: =J51*J53 -> 1.996341 | K54: =K51*K53 -> 1.4284241 | L54: =L51*L53 -> 0.70489071 | M54: =M51*M53 -> -0.15390405 | ... P54: =P51*P53 -> -3.4059254
B56: Other Balance Sheet Assumptions
B57: Other Asset Growth | F57: 0.02 | G57: =F57 -> 0.02 | H57: =G57 -> 0.02 | I57: =H57 -> 0.02 | J57: =I57 -> 0.02 | K57: =J57 -> 0.02 | L57: =K57 -> 0.02 | M57: =L57 -> 0.02 | N57: =M57 -> 0.02 | ... P57: =O57 -> 0.02
B59: Other Income Statement Assumptions
B60: Fee Income Ratio | F60: 0.2 | G60: =F60 -> 0.2 | H60: =G60 -> 0.2 | I60: =H60 -> 0.2 | J60: =I60 -> 0.2 | K60: =J60 -> 0.2 | L60: =K60 -> 0.2 | M60: =L60 -> 0.2 | N60: =M60 -> 0.2 | ... P60: =O60 -> 0.2
B61: Efficiency Ratio | F61: 0.6 | G61: =F61 -> 0.6 | H61: =G61 -> 0.6 | I61: =H61 -> 0.6 | J61: =I61 -> 0.6 | K61: =J61 -> 0.6 | L61: =K61 -> 0.6 | M61: =L61 -> 0.6 | N61: =M61 -> 0.6 | ... P61: =O61 -> 0.6
B62: Tax Rate | F62: 0.35 | G62: =F62 -> 0.35 | H62: =G62 -> 0.35 | I62: =H62 -> 0.35 | J62: =I62 -> 0.35 | K62: =J62 -> 0.35 | L62: =K62 -> 0.35 | M62: =L62 -> 0.35 | N62: =M62 -> 0.35 | ... P62: =O62 -> 0.35
B64: FINANCIAL STATEMENTS
A65: X
E67: =E$3 -> 41274 | F67: =F$3 -> 41639 | G67: =G$3 -> 42004 | H67: =H$3 -> 42369 | I67: =I$3 -> 42735 | J67: =J$3 -> 43100 | K67: =K$3 -> 43465 | L67: =L$3 -> 43830 | ... P67: =P$3 -> 45291
B69: Income Statement (Pre-Target Acquisition)
B70: Interest Income on Loans | F70: =F22 -> 77.45375 | G70: =G22 -> 83.188462 | H70: =H22 -> 87.718885 | I70: =I22 -> 91.297919 | J70: =J22 -> 94.125356 | K70: =K22 -> 96.359032 | L70: =L22 -> 98.123635 | M70: =M22 -> 99.517672 | ... P70: =P22 -> 102.17629
B71: Interest Income on Securities and Cash | F71: =F29+F34 -> 10.775634 | G71: =G29+G34 -> 12.719023 | H71: =H29+H34 -> 13.358447 | I71: =I29+I34 -> 13.870701 | J71: =J29+J34 -> 14.282631 | K71: =K29+K34 -> 14.615452 | L71: =L29+L34 -> 14.885924 | M71: =M29+M34 -> 15.107291 | ... P71: =P29+P34 -> 15.57091
B72: Interest Income | F72: =SUM(F70:F71) -> 88.229384 | G72: =SUM(G70:G71) -> 95.907486 | H72: =SUM(H70:H71) -> 101.07733 | I72: =SUM(I70:I71) -> 105.16862 | J72: =SUM(J70:J71) -> 108.40799 | K72: =SUM(K70:K71) -> 110.97448 | L72: =SUM(L70:L71) -> 113.00956 | M72: =SUM(M70:M71) -> 114.62496 | ... P72: =SUM(P70:P71) -> 117.7472
B73: Interest Expense | F73: =F49+F54 -> 9.3593284 | G73: =G49+G54 -> 10.532355 | H73: =H49+H54 -> 11.026997 | I73: =I49+I54 -> 11.281373 | J73: =J49+J54 -> 11.340545 | K73: =K49+K54 -> 11.239839 | L73: =L49+L54 -> 11.006876 | M73: =M49+M54 -> 10.66318 | ... P73: =P49+P54 -> 9.116202
B74: Net Interest Income Before Provisions | F74: =F72-F73 -> 78.870056 | G74: =G72-G73 -> 85.37513 | H74: =H72-H73 -> 90.050336 | I74: =I72-I73 -> 93.887247 | J74: =J72-J73 -> 97.067442 | K74: =K72-K73 -> 99.734645 | L74: =L72-L73 -> 102.00268 | M74: =M72-M73 -> 103.96178 | ... P74: =P72-P73 -> 108.631
B75: Loan Loss Provision | F75: =F40 -> 15.4975 | G75: =G40 -> 16.045525 | H75: =H40 -> 16.675965 | I75: =I40 -> 17.174012 | J75: =J40 -> 17.56747 | K75: =K40 -> 17.878301 | L75: =L40 -> 18.123858 | M75: =M40 -> 18.317848 | ... P75: =P40 -> 18.687813
B76: Net Interest Income After Provisions | F76: =F74-F75 -> 63.372556 | G76: =G74-G75 -> 69.329605 | H76: =H74-H75 -> 73.374371 | I76: =I74-I75 -> 76.713235 | J76: =J74-J75 -> 79.499973 | K76: =K74-K75 -> 81.856344 | L76: =L74-L75 -> 83.878825 | M76: =M74-M75 -> 85.643935 | ... P76: =P74-P75 -> 89.943188
B77: Non-Interest Income | F77: =(F76*F60)/(1-F60) -> 15.843139 | G77: =(G76*G60)/(1-G60) -> 17.332401 | H77: =(H76*H60)/(1-H60) -> 18.343593 | I77: =(I76*I60)/(1-I60) -> 19.178309 | J77: =(J76*J60)/(1-J60) -> 19.874993 | K77: =(K76*K60)/(1-K60) -> 20.464086 | L77: =(L76*L60)/(1-L60) -> 20.969706 | M77: =(M76*M60)/(1-M60) -> 21.410984 | ... P77: =(P76*P60)/(1-P60) -> 22.485797
B78: Total Revenue | F78: =F76+F77 -> 79.215695 | G78: =G76+G77 -> 86.662007 | H78: =H76+H77 -> 91.717964 | I78: =I76+I77 -> 95.891543 | J78: =J76+J77 -> 99.374966 | K78: =K76+K77 -> 102.32043 | L78: =L76+L77 -> 104.84853 | M78: =M76+M77 -> 107.05492 | ... P78: =P76+P77 -> 112.42899
B79: Operating Expense | F79: =F78*F61 -> 47.529417 | G79: =G78*G61 -> 51.997204 | H79: =H78*H61 -> 55.030778 | I79: =I78*I61 -> 57.534926 | J79: =J78*J61 -> 59.62498 | K79: =K78*K61 -> 61.392258 | L79: =L78*L61 -> 62.909119 | M79: =M78*M61 -> 64.232951 | ... P79: =P78*P61 -> 67.457391
B80: Amortization | F80: 0 | G80: 0 | H80: 0 | I80: 0 | J80: 0 | K80: 0 | L80: 0 | M80: 0 | N80: 0 | O80: 0 | P80: 0
B81: Total Expense | F81: =SUM(F79:F80) -> 47.529417 | G81: =SUM(G79:G80) -> 51.997204 | H81: =SUM(H79:H80) -> 55.030778 | I81: =SUM(I79:I80) -> 57.534926 | J81: =SUM(J79:J80) -> 59.62498 | K81: =SUM(K79:K80) -> 61.392258 | L81: =SUM(L79:L80) -> 62.909119 | M81: =SUM(M79:M80) -> 64.232951 | ... P81: =SUM(P79:P80) -> 67.457391
B82: Pre-Tax Income | F82: =F78-F81 -> 31.686278 | G82: =G78-G81 -> 34.664803 | H82: =H78-H81 -> 36.687186 | I82: =I78-I81 -> 38.356617 | J82: =J78-J81 -> 39.749986 | K82: =K78-K81 -> 40.928172 | L82: =L78-L81 -> 41.939413 | M82: =M78-M81 -> 42.821967 | ... P82: =P78-P81 -> 44.971594
B83: Tax Provision | F83: =F82*F62 -> 11.090197 | G83: =G82*G62 -> 12.132681 | H83: =H82*H62 -> 12.840515 | I83: =I82*I62 -> 13.424816 | J83: =J82*J62 -> 13.912495 | K83: =K82*K62 -> 14.32486 | L83: =L82*L62 -> 14.678794 | M83: =M82*M62 -> 14.987689 | ... P83: =P82*P62 -> 15.740058
B84: Net Income | F84: =F82-F83 -> 20.596081 | G84: =G82-G83 -> 22.532122 | H84: =H82-H83 -> 23.846671 | I84: =I82-I83 -> 24.931801 | J84: =J82-J83 -> 25.837491 | K84: =K82-K83 -> 26.603312 | L84: =L82-L83 -> 27.260618 | M84: =M82-M83 -> 27.834279 | ... P84: =P82-P83 -> 29.231536
B85: Preferred Dividends | F85: 0 | G85: 0 | H85: 0 | I85: 0 | J85: 0 | K85: 0 | L85: 0 | M85: 0 | N85: 0 | O85: 0 | P85: 0
B86: Net Income to Common | F86: =F84-F85 -> 20.596081 | G86: =G84-G85 -> 22.532122 | H86: =H84-H85 -> 23.846671 | I86: =I84-I85 -> 24.931801 | J86: =J84-J85 -> 25.837491 | K86: =K84-K85 -> 26.603312 | L86: =L84-L85 -> 27.260618 | M86: =M84-M85 -> 27.834279 | ... P86: =P84-P85 -> 29.231536
B88: Balance Sheet
B89: Assets: | E89: Opening
B90: Cash and Equivalents | E90: 75 | F90: =E90*(1+F$57) -> 76.5 | G90: =F90*(1+G$57) -> 78.03 | H90: =G90*(1+H$57) -> 79.5906 | I90: =H90*(1+I$57) -> 81.182412 | J90: =I90*(1+J$57) -> 82.80606 | K90: =J90*(1+K$57) -> 84.462181 | L90: =K90*(1+L$57) -> 86.151425 | M90: =L90*(1+M$57) -> 87.874454 | ... P90: =O90*(1+P$57) -> 93.253073 | R90: B/S Growth
B91: Securities | E91: 300 | F91: =(SUM(F90,F94:F99)*F$25)/(1-F$25) -> 405.75063 | G91: =(SUM(G90,G94:G99)*G$25)/(1-G$25) -> 429.30674 | H91: =(SUM(H90,H94:H99)*H$25)/(1-H$25) -> 448.12135 | I91: =(SUM(I90,I94:I99)*I$25)/(1-I$25) -> 463.19427 | J91: =(SUM(J90,J94:J99)*J$25)/(1-J$25) -> 475.31545 | K91: =(SUM(K90,K94:K99)*K$25)/(1-K$25) -> 485.10902 | L91: =(SUM(L90,L94:L99)*L$25)/(1-L$25) -> 493.06813 | M91: =(SUM(M90,M94:M99)*M$25)/(1-M$25) -> 499.58248 | ... P91: =(SUM(P90,P94:P99)*P$25)/(1-P$25) -> 513.22689 | R91: Constant % of B/S
B92: Loans, Gross | E92: 1350 | F92: =F20 -> 1466.5 | G92: =G20 -> 1558.535 | H92: =H20 -> 1631.2426 | I92: =I20 -> 1688.6817 | J92: =J20 -> 1734.0585 | K92: =K20 -> 1769.9062 | L92: =L20 -> 1798.2259 | M92: =M20 -> 1820.5985 | ... P92: =P20 -> 1863.2661
B93: Loan Loss Reserve | E93: 20 | F93: =F42 -> 21.9975 | G93: =G42 -> 23.378025 | H93: =H42 -> 24.46864 | I93: =I42 -> 25.330225 | J93: =J42 -> 26.010878 | K93: =K42 -> 26.548594 | L93: =L42 -> 26.973389 | M93: =M42 -> 27.308977 | ... P93: =P42 -> 27.948991
B94: Loans, Net | E94: =E92-E93 -> 1330 | F94: =F92-F93 -> 1444.5025 | G94: =G92-G93 -> 1535.157 | H94: =H92-H93 -> 1606.774 | I94: =I92-I93 -> 1663.3515 | J94: =J92-J93 -> 1708.0477 | K94: =K92-K93 -> 1743.3577 | L94: =L92-L93 -> 1771.2525 | ... P94: =P92-P93 -> 1835.3171 | R94: Roll Forward
B95: Goodwill | E95: 0 | F95: =E95 -> 0 | G95: =F95 -> 0 | H95: =G95 -> 0 | I95: =H95 -> 0 | J95: =I95 -> 0 | K95: =J95 -> 0 | L95: =K95 -> 0 | M95: =L95 -> 0 | ... P95: =O95 -> 0 | R95: FLAT
B96: Other Intangibles (CDI) | E96: 0 | F96: =E96 -> 0 | G96: =F96 -> 0 | H96: =G96 -> 0 | I96: =H96 -> 0 | J96: =I96 -> 0 | K96: =J96 -> 0 | L96: =K96 -> 0 | M96: =L96 -> 0 | ... P96: =O96 -> 0 | R96: FLAT
B97: Other Real Estate Owned | E97: 0 | F97: =E97 -> 0 | G97: =F97 -> 0 | H97: =G97 -> 0 | I97: =H97 -> 0 | J97: =I97 -> 0 | K97: =J97 -> 0 | L97: =K97 -> 0 | M97: =L97 -> 0 | ... P97: =O97 -> 0 | R97: FLAT
B98: Fixed Assets | E98: 50 | F98: =E98*(1+F$57) -> 51 | G98: =F98*(1+G$57) -> 52.02 | H98: =G98*(1+H$57) -> 53.0604 | I98: =H98*(1+I$57) -> 54.121608 | J98: =I98*(1+J$57) -> 55.20404 | K98: =J98*(1+K$57) -> 56.308121 | L98: =K98*(1+L$57) -> 57.434283 | M98: =L98*(1+M$57) -> 58.582969 | ... P98: =O98*(1+P$57) -> 62.168715 | R98: B/S Growth
B99: Other Assets | E99: 50 | F99: =E99*(1+F$57) -> 51 | G99: =F99*(1+G$57) -> 52.02 | H99: =G99*(1+H$57) -> 53.0604 | I99: =H99*(1+I$57) -> 54.121608 | J99: =I99*(1+J$57) -> 55.20404 | K99: =J99*(1+K$57) -> 56.308121 | L99: =K99*(1+L$57) -> 57.434283 | M99: =L99*(1+M$57) -> 58.582969 | ... P99: =O99*(1+P$57) -> 62.168715 | R99: B/S Growth
B100: Total Assets | E100: =SUM(E90:E91,E94:E99) -> 1805 | F100: =SUM(F90:F91,F94:F99) -> 2028.7531 | G100: =SUM(G90:G91,G94:G99) -> 2146.5337 | H100: =SUM(H90:H91,H94:H99) -> 2240.6068 | I100: =SUM(I90:I91,I94:I99) -> 2315.9714 | J100: =SUM(J90:J91,J94:J99) -> 2376.5773 | K100: =SUM(K90:K91,K94:K99) -> 2425.5451 | L100: =SUM(L90:L91,L94:L99) -> 2465.3407 | ... P100: =SUM(P90:P91,P94:P99) -> 2566.1345
B102: Liabilities:
B103: Deposits | E103: 1500 | F103: =F47 -> 1575 | G103: =G47 -> 1653.75 | H103: =H47 -> 1736.4375 | I103: =I47 -> 1823.2594 | J103: =J47 -> 1914.4223 | K103: =K47 -> 2010.1435 | L103: =L47 -> 2110.6506 | M103: =M47 -> 2216.1832 | ... P103: =P47 -> 2565.509 | R103: Deposit Growth
B104: Borrowings | E104: 100 | F104: =F100-F103-F105-F110 -> 234.36567 | G104: =G100-G103-G105-G110 -> 257.73039 | H104: =H100-H103-H105-H110 -> 252.5752 | I104: =I100-I103-I105-I110 -> 223.85105 | J104: =J100-J103-J105-J110 -> 175.41716 | K104: =K100-K103-K105-K110 -> 110.26765 | L104: =L100-L103-L105-L110 -> 30.710491 | M104: =M100-M103-M105-M110 -> -61.491301 | ... P104: =P100-P103-P105-P110 -> -402.32861 | R104: PLUG
B105: Other Liabilities | E105: 50 | F105: =E105*(1+F$57) -> 51 | G105: =F105*(1+G$57) -> 52.02 | H105: =G105*(1+H$57) -> 53.0604 | I105: =H105*(1+I$57) -> 54.121608 | J105: =I105*(1+J$57) -> 55.20404 | K105: =J105*(1+K$57) -> 56.308121 | L105: =K105*(1+L$57) -> 57.434283 | M105: =L105*(1+M$57) -> 58.582969 | ... P105: =O105*(1+P$57) -> 62.168715 | R105: B/S Growth
B106: Total Liabilities | E106: =SUM(E103:E105) -> 1650 | F106: =SUM(F103:F105) -> 1860.3657 | G106: =SUM(G103:G105) -> 1963.5004 | H106: =SUM(H103:H105) -> 2042.0731 | I106: =SUM(I103:I105) -> 2101.232 | J106: =SUM(J103:J105) -> 2145.0435 | K106: =SUM(K103:K105) -> 2176.7192 | L106: =SUM(L103:L105) -> 2198.7954 | ... P106: =SUM(P103:P105) -> 2225.3491
B108: Equity:
B109: Preferred Equity | E109: 0 | F109: =E109 -> 0 | G109: =F109 -> 0 | H109: =G109 -> 0 | I109: =H109 -> 0 | J109: =I109 -> 0 | K109: =J109 -> 0 | L109: =K109 -> 0 | M109: =L109 -> 0 | ... P109: =O109 -> 0
B110: Common Equity | E110: =E100-E106 -> 155 | F110: =F128 -> 168.38745 | G110: =G128 -> 183.03333 | H110: =H128 -> 198.53367 | I110: =I128 -> 214.73934 | J110: =J128 -> 231.53371 | K110: =K128 -> 248.82586 | L110: =L128 -> 266.54526 | M110: =M128 -> 284.63754 | ... P110: =P128 -> 340.78532 | R110: Roll Forward
B111: Total Equity | E111: =SUM(E109:E110) -> 155 | F111: =SUM(F109:F110) -> 168.38745 | G111: =SUM(G109:G110) -> 183.03333 | H111: =SUM(H109:H110) -> 198.53367 | I111: =SUM(I109:I110) -> 214.73934 | J111: =SUM(J109:J110) -> 231.53371 | K111: =SUM(K109:K110) -> 248.82586 | L111: =SUM(L109:L110) -> 266.54526 | ... P111: =SUM(P109:P110) -> 340.78532
B112: Total Liabilities and Equity | E112: =E106+E111 -> 1805 | F112: =F106+F111 -> 2028.7531 | G112: =G106+G111 -> 2146.5337 | H112: =H106+H111 -> 2240.6068 | I112: =I106+I111 -> 2315.9714 | J112: =J106+J111 -> 2376.5773 | K112: =K106+K111 -> 2425.5451 | L112: =L106+L111 -> 2465.3407 | ... P112: =P106+P111 -> 2566.1345
B113: Check | E113: =E112-E100 -> 0 | F113: =F112-F100 -> 0 | G113: =G112-G100 -> 0 | H113: =H112-H100 -> 0 | I113: =I112-I100 -> 0 | J113: =J112-J100 -> 0 | K113: =K112-K100 -> 0 | L113: =L112-L100 -> 0 | ... P113: =P112-P100 -> 0
B115: KEY METRICS AND SUPPORTING SCHEDULES
A116: X
E118: =E$3 -> 41274 | F118: =F$3 -> 41639 | G118: =G$3 -> 42004 | H118: =H$3 -> 42369 | I118: =I$3 -> 42735 | J118: =J$3 -> 43100 | K118: =K$3 -> 43465 | L118: =L$3 -> 43830 | ... P118: =P$3 -> 45291
B120: Capital
...

Sheet loan
B1: Standard Operating Model
B3: LOAN SCHEDULE
A4: X
E6: =model!E3 -> 41274 | F6: =model!F3 -> 41639 | G6: =model!G3 -> 42004 | H6: =model!H3 -> 42369 | I6: =model!I3 -> 42735 | J6: =model!J3 -> 43100 | K6: =model!K3 -> 43465 | L6: =model!L3 -> 43830 | ... P6: =model!P3 -> 45291
B8: Scheduled Amortization
C10: Maturity
B11: {=TRANSPOSE($E$6:$P$6)} -> 41274 | C11: 5 | E11: =-$C45/$C11*0.5 -> -20 | F11: =IF((E45+F28)<$C45/$C11,-(E45+F28),-$C45/$C11) -> -40 | G11: =IF((F45+G28)<$C45/$C11,-(F45+G28),-$C45/$C11) -> -40 | H11: =IF((G45+H28)<$C45/$C11,-(G45+H28),-$C45/$C11) -> -40 | I11: =IF((H45+I28)<$C45/$C11,-(H45+I28),-$C45/$C11) -> -40 | J11: =IF((I45+J28)<$C45/$C11,-(I45+J28),-$C45/$C11) -> -14.187419 | K11: =IF((J45+K28)<$C45/$C11,-(J45+K28),-$C45/$C11) -> 0 | L11: =IF((K45+L28)<$C45/$C11,-(K45+L28),-$C45/$C11) -> 0 | M11: =IF((L45+M28)<$C45/$C11,-(L45+M28),-$C45/$C11) -> 0 | ... P11: =IF((O45+P28)<$C45/$C11,-(O45+P28),-$C45/$C11) -> 0
B12: 41639 | C12: =C11 -> 5 | F12: =-$C46/$C12*0.5 -> -20 | G12: =IF((F46+G29)<$C46/$C12,-(F46+G29),-$C46/$C12) -> -40 | H12: =IF((G46+H29)<$C46/$C12,-(G46+H29),-$C46/$C12) -> -40 | I12: =IF((H46+I29)<$C46/$C12,-(H46+I29),-$C46/$C12) -> -40 | J12: =IF((I46+J29)<$C46/$C12,-(I46+J29),-$C46/$C12) -> -40 | K12: =IF((J46+K29)<$C46/$C12,-(J46+K29),-$C46/$C12) -> -14.187419 | L12: =IF((K46+L29)<$C46/$C12,-(K46+L29),-$C46/$C12) -> 0 | M12: =IF((L46+M29)<$C46/$C12,-(L46+M29),-$C46/$C12) -> 0 | N12: =IF((M46+N29)<$C46/$C12,-(M46+N29),-$C46/$C12) -> 0 | ... P12: =IF((O46+P29)<$C46/$C12,-(O46+P29),-$C46/$C12) -> 0
B13: 42004 | C13: =C12 -> 5 | G13: =-$C47/$C13*0.5 -> -20 | H13: =IF((G47+H30)<$C47/$C13,-(G47+H30),-$C47/$C13) -> -40 | I13: =IF((H47+I30)<$C47/$C13,-(H47+I30),-$C47/$C13) -> -40 | J13: =IF((I47+J30)<$C47/$C13,-(I47+J30),-$C47/$C13) -> -40 | K13: =IF((J47+K30)<$C47/$C13,-(J47+K30),-$C47/$C13) -> -40 | L13: =IF((K47+L30)<$C47/$C13,-(K47+L30),-$C47/$C13) -> -14.187419 | M13: =IF((L47+M30)<$C47/$C13,-(L47+M30),-$C47/$C13) -> 0 | N13: =IF((M47+N30)<$C47/$C13,-(M47+N30),-$C47/$C13) -> 0 | O13: =IF((N47+O30)<$C47/$C13,-(N47+O30),-$C47/$C13) -> 0 | P13: =IF((O47+P30)<$C47/$C13,-(O47+P30),-$C47/$C13) -> 0
B14: 42369 | C14: =C13 -> 5 | H14: =-$C48/$C14*0.5 -> -20 | I14: =IF((H48+I31)<$C48/$C14,-(H48+I31),-$C48/$C14) -> -40 | J14: =IF((I48+J31)<$C48/$C14,-(I48+J31),-$C48/$C14) -> -40 | K14: =IF((J48+K31)<$C48/$C14,-(J48+K31),-$C48/$C14) -> -40 | L14: =IF((K48+L31)<$C48/$C14,-(K48+L31),-$C48/$C14) -> -40 | M14: =IF((L48+M31)<$C48/$C14,-(L48+M31),-$C48/$C14) -> -14.187419 | N14: =IF((M48+N31)<$C48/$C14,-(M48+N31),-$C48/$C14) -> 0 | O14: =IF((N48+O31)<$C48/$C14,-(N48+O31),-$C48/$C14) -> 0 | P14: =IF((O48+P31)<$C48/$C14,-(O48+P31),-$C48/$C14) -> 0
B15: 42735 | C15: =C14 -> 5 | I15: =-$C49/$C15*0.5 -> -20 | J15: =IF((I49+J32)<$C49/$C15,-(I49+J32),-$C49/$C15) -> -40 | K15: =IF((J49+K32)<$C49/$C15,-(J49+K32),-$C49/$C15) -> -40 | L15: =IF((K49+L32)<$C49/$C15,-(K49+L32),-$C49/$C15) -> -40 | M15: =IF((L49+M32)<$C49/$C15,-(L49+M32),-$C49/$C15) -> -40 | N15: =IF((M49+N32)<$C49/$C15,-(M49+N32),-$C49/$C15) -> -14.187419 | O15: =IF((N49+O32)<$C49/$C15,-(N49+O32),-$C49/$C15) -> 0 | P15: =IF((O49+P32)<$C49/$C15,-(O49+P32),-$C49/$C15) -> 0
B16: 43100 | C16: =C15 -> 5 | J16: =-$C50/$C16*0.5 -> -20 | K16: =IF((J50+K33)<$C50/$C16,-(J50+K33),-$C50/$C16) -> -40 | L16: =IF((K50+L33)<$C50/$C16,-(K50+L33),-$C50/$C16) -> -40 | M16: =IF((L50+M33)<$C50/$C16,-(L50+M33),-$C50/$C16) -> -40 | N16: =IF((M50+N33)<$C50/$C16,-(M50+N33),-$C50/$C16) -> -40 | O16: =IF((N50+O33)<$C50/$C16,-(N50+O33),-$C50/$C16) -> -14.187419 | P16: =IF((O50+P33)<$C50/$C16,-(O50+P33),-$C50/$C16) -> 0
B17: 43465 | C17: =C16 -> 5 | K17: =-$C51/$C17*0.5 -> -20 | L17: =IF((K51+L34)<$C51/$C17,-(K51+L34),-$C51/$C17) -> -40 | M17: =IF((L51+M34)<$C51/$C17,-(L51+M34),-$C51/$C17) -> -40 | N17: =IF((M51+N34)<$C51/$C17,-(M51+N34),-$C51/$C17) -> -40 | O17: =IF((N51+O34)<$C51/$C17,-(N51+O34),-$C51/$C17) -> -40 | P17: =IF((O51+P34)<$C51/$C17,-(O51+P34),-$C51/$C17) -> -14.187419
B18: 43830 | C18: =C17 -> 5 | L18: =-$C52/$C18*0.5 -> -20 | M18: =IF((L52+M35)<$C52/$C18,-(L52+M35),-$C52/$C18) -> -40 | N18: =IF((M52+N35)<$C52/$C18,-(M52+N35),-$C52/$C18) -> -40 | O18: =IF((N52+O35)<$C52/$C18,-(N52+O35),-$C52/$C18) -> -40 | P18: =IF((O52+P35)<$C52/$C18,-(O52+P35),-$C52/$C18) -> -40
B19: 44196 | C19: =C18 -> 5 | M19: =-$C53/$C19*0.5 -> -20 | N19: =IF((M53+N36)<$C53/$C19,-(M53+N36),-$C53/$C19) -> -40 | O19: =IF((N53+O36)<$C53/$C19,-(N53+O36),-$C53/$C19) -> -40 | P19: =IF((O53+P36)<$C53/$C19,-(O53+P36),-$C53/$C19) -> -40
B20: 44561 | C20: =C19 -> 5 | N20: =-$C54/$C20*0.5 -> -20 | O20: =IF((N54+O37)<$C54/$C20,-(N54+O37),-$C54/$C20) -> -40 | P20: =IF((O54+P37)<$C54/$C20,-(O54+P37),-$C54/$C20) -> -40
B21: 44926 | C21: =C20 -> 5 | O21: =-$C55/$C21*0.5 -> -20 | P21: =IF((O55+P38)<$C55/$C21,-(O55+P38),-$C55/$C21) -> -40
B22: 45291 | C22: =C21 -> 5 | P22: =-$C56/$C22*0.5 -> -20
B23: Total Originations | E23: =SUM(E11:E22) -> -20 | F23: =SUM(F11:F22) -> -60 | G23: =SUM(G11:G22) -> -100 | H23: =SUM(H11:H22) -> -140 | I23: =SUM(I11:I22) -> -180 | J23: =SUM(J11:J22) -> -194.18742 | K23: =SUM(K11:K22) -> -194.18742 | L23: =SUM(L11:L22) -> -194.18742 | ... P23: =SUM(P11:P22) -> -194.18742
B25: Net Credit Losses
C27: NCOs
B28: {=TRANSPOSE($E$6:$P$6)} -> 41274 | C28: 0.01 | E28: =-($C45)*$C$28*0.5 -> -1 | F28: =-(E45)*$C$28 -> -1.79 | G28: =-(F45)*$C$28 -> -1.3721 | H28: =-(G45)*$C$28 -> -0.958379 | I28: =-(H45)*$C$28 -> -0.54879521 | J28: =-(I45)*$C$28 -> -0.14330726 | K28: =-(J45)*$C$28 -> 0 | L28: =-(K45)*$C$28 -> 0 | M28: =-(L45)*$C$28 -> 0 | ... P28: =-(O45)*$C$28 -> 0
B29: 41639 | C29: =C28 -> 0.01 | F29: =-($C46)*$C$28*0.5 -> -1 | G29: =-(F46)*$C$28 -> -1.79 | H29: =-(G46)*$C$28 -> -1.3721 | I29: =-(H46)*$C$28 -> -0.958379 | J29: =-(I46)*$C$28 -> -0.54879521 | K29: =-(J46)*$C$28 -> -0.14330726 | L29: =-(K46)*$C$28 -> 0 | M29: =-(L46)*$C$28 -> 0 | N29: =-(M46)*$C$28 -> 0 | ... P29: =-(O46)*$C$28 -> 0
B30: 42004 | C30: =C29 -> 0.01 | G30: =-($C47)*$C$28*0.5 -> -1 | H30: =-(G47)*$C$28 -> -1.79 | I30: =-(H47)*$C$28 -> -1.3721 | J30: =-(I47)*$C$28 -> -0.958379 | K30: =-(J47)*$C$28 -> -0.54879521 | L30: =-(K47)*$C$28 -> -0.14330726 | M30: =-(L47)*$C$28 -> 0 | N30: =-(M47)*$C$28 -> 0 | O30: =-(N47)*$C$28 -> 0 | P30: =-(O47)*$C$28 -> 0
B31: 42369 | C31: =C30 -> 0.01 | H31: =-($C48)*$C$28*0.5 -> -1 | I31: =-(H48)*$C$28 -> -1.79 | J31: =-(I48)*$C$28 -> -1.3721 | K31: =-(J48)*$C$28 -> -0.958379 | L31: =-(K48)*$C$28 -> -0.54879521 | M31: =-(L48)*$C$28 -> -0.14330726 | N31: =-(M48)*$C$28 -> 0 | O31: =-(N48)*$C$28 -> 0 | P31: =-(O48)*$C$28 -> 0
B32: 42735 | C32: =C31 -> 0.01 | I32: =-($C49)*$C$28*0.5 -> -1 | J32: =-(I49)*$C$28 -> -1.79 | K32: =-(J49)*$C$28 -> -1.3721 | L32: =-(K49)*$C$28 -> -0.958379 | M32: =-(L49)*$C$28 -> -0.54879521 | N32: =-(M49)*$C$28 -> -0.14330726 | O32: =-(N49)*$C$28 -> 0 | P32: =-(O49)*$C$28 -> 0
B33: 43100 | C33: =C32 -> 0.01 | J33: =-($C50)*$C$28*0.5 -> -1 | K33: =-(J50)*$C$28 -> -1.79 | L33: =-(K50)*$C$28 -> -1.3721 | M33: =-(L50)*$C$28 -> -0.958379 | N33: =-(M50)*$C$28 -> -0.54879521 | O33: =-(N50)*$C$28 -> -0.14330726 | P33: =-(O50)*$C$28 -> 0
B34: 43465 | C34: =C33 -> 0.01 | K34: =-($C51)*$C$28*0.5 -> -1 | L34: =-(K51)*$C$28 -> -1.79 | M34: =-(L51)*$C$28 -> -1.3721 | N34: =-(M51)*$C$28 -> -0.958379 | O34: =-(N51)*$C$28 -> -0.54879521 | P34: =-(O51)*$C$28 -> -0.14330726
B35: 43830 | C35: =C34 -> 0.01 | L35: =-($C52)*$C$28*0.5 -> -1 | M35: =-(L52)*$C$28 -> -1.79 | N35: =-(M52)*$C$28 -> -1.3721 | O35: =-(N52)*$C$28 -> -0.958379 | P35: =-(O52)*$C$28 -> -0.54879521
B36: 44196 | C36: =C35 -> 0.01 | M36: =-($C53)*$C$28*0.5 -> -1 | N36: =-(M53)*$C$28 -> -1.79 | O36: =-(N53)*$C$28 -> -1.3721 | P36: =-(O53)*$C$28 -> -0.958379
B37: 44561 | C37: =C36 -> 0.01 | N37: =-($C54)*$C$28*0.5 -> -1 | O37: =-(N54)*$C$28 -> -1.79 | P37: =-(O54)*$C$28 -> -1.3721
B38: 44926 | C38: =C37 -> 0.01 | O38: =-($C55)*$C$28*0.5 -> -1 | P38: =-(O55)*$C$28 -> -1.79
B39: 45291 | C39: =C38 -> 0.01 | P39: =-($C56)*$C$28*0.5 -> -1
B40: Total Net Credit Losses | E40: =SUM(E28:E39) -> -1 | F40: =SUM(F28:F39) -> -2.79 | G40: =SUM(G28:G39) -> -4.1621 | H40: =SUM(H28:H39) -> -5.120479 | I40: =SUM(I28:I39) -> -5.6692742 | J40: =SUM(J28:J39) -> -5.8125815 | K40: =SUM(K28:K39) -> -5.8125815 | L40: =SUM(L28:L39) -> -5.8125815 | ... P40: =SUM(P28:P39) -> -5.8125815
B42: Period-End Balance
C44: Origination
B45: {=TRANSPOSE($E$6:$P$6)} -> 41274 | C45: 200 | D45: 0 | E45: =$C45+E11+E28 -> 179 | F45: =E45+F11+F28 -> 137.21 | G45: =F45+G11+G28 -> 95.8379 | H45: =G45+H11+H28 -> 54.879521 | I45: =H45+I11+I28 -> 14.330726 | J45: =I45+J11+J28 -> 0 | K45: =J45+K11+K28 -> 0 | L45: =K45+L11+L28 -> 0 | M45: =L45+M11+M28 -> 0 | ... P45: =O45+P11+P28 -> 0
B46: 41639 | C46: =C45 -> 200 | E46: 0 | F46: =$C46+F12+F29 -> 179 | G46: =F46+G12+G29 -> 137.21 | H46: =G46+H12+H29 -> 95.8379 | I46: =H46+I12+I29 -> 54.879521 | J46: =I46+J12+J29 -> 14.330726 | K46: =J46+K12+K29 -> 0 | L46: =K46+L12+L29 -> 0 | M46: =L46+M12+M29 -> 0 | N46: =M46+N12+N29 -> 0 | ... P46: =O46+P12+P29 -> 0
B47: 42004 | C47: =C46 -> 200 | F47: 0 | G47: =$C47+G13+G30 -> 179 | H47: =G47+H13+H30 -> 137.21 | I47: =H47+I13+I30 -> 95.8379 | J47: =I47+J13+J30 -> 54.879521 | K47: =J47+K13+K30 -> 14.330726 | L47: =K47+L13+L30 -> 0 | M47: =L47+M13+M30 -> 0 | N47: =M47+N13+N30 -> 0 | O47: =N47+O13+O30 -> 0 | P47: =O47+P13+P30 -> 0
B48: 42369 | C48: =C47 -> 200 | G48: 0 | H48: =$C48+H14+H31 -> 179 | I48: =H48+I14+I31 -> 137.21 | J48: =I48+J14+J31 -> 95.8379 | K48: =J48+K14+K31 -> 54.879521 | L48: =K48+L14+L31 -> 14.330726 | M48: =L48+M14+M31 -> 0 | N48: =M48+N14+N31 -> 0 | O48: =N48+O14+O31 -> 0 | P48: =O48+P14+P31 -> 0
B49: 42735 | C49: =C48 -> 200 | H49: 0 | I49: =$C49+I15+I32 -> 179 | J49: =I49+J15+J32 -> 137.21 | K49: =J49+K15+K32 -> 95.8379 | L49: =K49+L15+L32 -> 54.879521 | M49: =L49+M15+M32 -> 14.330726 | N49: =M49+N15+N32 -> 0 | O49: =N49+O15+O32 -> 0 | P49: =O49+P15+P32 -> 0
B50: 43100 | C50: =C49 -> 200 | I50: 0 | J50: =$C50+J16+J33 -> 179 | K50: =J50+K16+K33 -> 137.21 | L50: =K50+L16+L33 -> 95.8379 | M50: =L50+M16+M33 -> 54.879521 | N50: =M50+N16+N33 -> 14.330726 | O50: =N50+O16+O33 -> 0 | P50: =O50+P16+P33 -> 0
B51: 43465 | C51: =C50 -> 200 | J51: 0 | K51: =$C51+K17+K34 -> 179 | L51: =K51+L17+L34 -> 137.21 | M51: =L51+M17+M34 -> 95.8379 | N51: =M51+N17+N34 -> 54.879521 | O51: =N51+O17+O34 -> 14.330726 | P51: =O51+P17+P34 -> 0
B52: 43830 | C52: =C51 -> 200 | K52: 0 | L52: =$C52+L18+L35 -> 179 | M52: =L52+M18+M35 -> 137.21 | N52: =M52+N18+N35 -> 95.8379 | O52: =N52+O18+O35 -> 54.879521 | P52: =O52+P18+P35 -> 14.330726
B53: 44196 | C53: =C52 -> 200 | L53: 0 | M53: =$C53+M19+M36 -> 179 | N53: =M53+N19+N36 -> 137.21 | O53: =N53+O19+O36 -> 95.8379 | P53: =O53+P19+P36 -> 54.879521
B54: 44561 | C54: =C53 -> 200 | M54: 0 | N54: =$C54+N20+N37 -> 179 | O54: =N54+O20+O37 -> 137.21 | P54: =O54+P20+P37 -> 95.8379
B55: 44926 | C55: =C54 -> 200 | N55: 0 | O55: =$C55+O21+O38 -> 179 | P55: =O55+P21+P38 -> 137.21
B56: 45291 | C56: =C55 -> 200 | O56: 0 | P56: =$C56+P22+P39 -> 179
B57: Total Period-End Balance | E57: =SUM(E45:E56) -> 179 | F57: =SUM(F45:F56) -> 316.21 | G57: =SUM(G45:G56) -> 412.0479 | H57: =SUM(H45:H56) -> 466.92742 | I57: =SUM(I45:I56) -> 481.25815 | J57: =SUM(J45:J56) -> 481.25815 | K57: =SUM(K45:K56) -> 481.25815 | L57: =SUM(L45:L56) -> 481.25815 | ... P57: =SUM(P45:P56) -> 481.25815
B59: Average Balance
B62: {=TRANSPOSE($E$6:$P$6)} -> 41274 | E62: =AVERAGE(D45:E45) -> 89.5 | F62: =AVERAGE(E45:F45) -> 158.105 | G62: =AVERAGE(F45:G45) -> 116.52395 | H62: =AVERAGE(G45:H45) -> 75.358711 | I62: =AVERAGE(H45:I45) -> 34.605123 | J62: =AVERAGE(I45:J45) -> 7.1653629 | K62: =AVERAGE(J45:K45) -> 0 | L62: =AVERAGE(K45:L45) -> 0 | ... P62: =AVERAGE(O45:P45) -> 0
B63: 41639 | F63: =AVERAGE(E46:F46) -> 89.5 | G63: =AVERAGE(F46:G46) -> 158.105 | H63: =AVERAGE(G46:H46) -> 116.52395 | I63: =AVERAGE(H46:I46) -> 75.358711 | J63: =AVERAGE(I46:J46) -> 34.605123 | K63: =AVERAGE(J46:K46) -> 7.1653629 | L63: =AVERAGE(K46:L46) -> 0 | M63: =AVERAGE(L46:M46) -> 0 | ... P63: =AVERAGE(O46:P46) -> 0
B64: 42004 | G64: =AVERAGE(F47:G47) -> 89.5 | H64: =AVERAGE(G47:H47) -> 158.105 | I64: =AVERAGE(H47:I47) -> 116.52395 | J64: =AVERAGE(I47:J47) -> 75.358711 | K64: =AVERAGE(J47:K47) -> 34.605123 | L64: =AVERAGE(K47:L47) -> 7.1653629 | M64: =AVERAGE(L47:M47) -> 0 | N64: =AVERAGE(M47:N47) -> 0 | ... P64: =AVERAGE(O47:P47) -> 0
B65: 42369 | H65: =AVERAGE(G48:H48) -> 89.5 | I65: =AVERAGE(H48:I48) -> 158.105 | J65: =AVERAGE(I48:J48) -> 116.52395 | K65: =AVERAGE(J48:K48) -> 75.358711 | L65: =AVERAGE(K48:L48) -> 34.605123 | M65: =AVERAGE(L48:M48) -> 7.1653629 | N65: =AVERAGE(M48:N48) -> 0 | O65: =AVERAGE(N48:O48) -> 0 | P65: =AVERAGE(O48:P48) -> 0
B66: 42735 | I66: =AVERAGE(H49:I49) -> 89.5 | J66: =AVERAGE(I49:J49) -> 158.105 | K66: =AVERAGE(J49:K49) -> 116.52395 | L66: =AVERAGE(K49:L49) -> 75.358711 | M66: =AVERAGE(L49:M49) -> 34.605123 | N66: =AVERAGE(M49:N49) -> 7.1653629 | O66: =AVERAGE(N49:O49) -> 0 | P66: =AVERAGE(O49:P49) -> 0
B67: 43100 | J67: =AVERAGE(I50:J50) -> 89.5 | K67: =AVERAGE(J50:K50) -> 158.105 | L67: =AVERAGE(K50:L50) -> 116.52395 | M67: =AVERAGE(L50:M50) -> 75.358711 | N67: =AVERAGE(M50:N50) -> 34.605123 | O67: =AVERAGE(N50:O50) -> 7.1653629 | P67: =AVERAGE(O50:P50) -> 0
B68: 43465 | K68: =AVERAGE(J51:K51) -> 89.5 | L68: =AVERAGE(K51:L51) -> 158.105 | M68: =AVERAGE(L51:M51) -> 116.52395 | N68: =AVERAGE(M51:N51) -> 75.358711 | O68: =AVERAGE(N51:O51) -> 34.605123 | P68: =AVERAGE(O51:P51) -> 7.1653629
B69: 43830 | L69: =AVERAGE(K52:L52) -> 89.5 | M69: =AVERAGE(L52:M52) -> 158.105 | N69: =AVERAGE(M52:N52) -> 116.52395 | O69: =AVERAGE(N52:O52) -> 75.358711 | P69: =AVERAGE(O52:P52) -> 34.605123
B70: 44196 | M70: =AVERAGE(L53:M53) -> 89.5 | N70: =AVERAGE(M53:N53) -> 158.105 | O70: =AVERAGE(N53:O53) -> 116.52395 | P70: =AVERAGE(O53:P53) -> 75.358711
B71: 44561 | N71: =AVERAGE(M54:N54) -> 89.5 | O71: =AVERAGE(N54:O54) -> 158.105 | P71: =AVERAGE(O54:P54) -> 116.52395
B72: 44926 | O72: =AVERAGE(N55:O55) -> 89.5 | P72: =AVERAGE(O55:P55) -> 158.105
B73: 45291 | P73: =AVERAGE(O56:P56) -> 89.5
B74: Total Average Balance | E74: =SUM(E62:E73) -> 89.5 | F74: =SUM(F62:F73) -> 247.605 | G74: =SUM(G62:G73) -> 364.12895 | H74: =SUM(H62:H73) -> 439.48766 | I74: =SUM(I62:I73) -> 474.09278 | J74: =SUM(J62:J73) -> 481.25815 | K74: =SUM(K62:K73) -> 481.25815 | L74: =SUM(L62:L73) -> 481.25815 | ... P74: =SUM(P62:P73) -> 481.25815
B76: Interest Income
C78: Coupon/Spread
B79: {=TRANSPOSE($E$6:$P$6)} -> 41274 | C79: 0.055 | E79: =$C79*E62 -> 4.9225 | F79: =$C79*F62 -> 8.695775 | G79: =$C79*G62 -> 6.4088173 | H79: =$C79*H62 -> 4.1447291 | I79: =$C79*I62 -> 1.9032818 | J79: =$C79*J62 -> 0.39409496 | K79: =$C79*K62 -> 0 | L79: =$C79*L62 -> 0 | ... P79: =$C79*P62 -> 0
B80: 41639 | C80: =C79 -> 0.055 | F80: =$C80*F63 -> 4.9225 | G80: =$C80*G63 -> 8.695775 | H80: =$C80*H63 -> 6.4088173 | I80: =$C80*I63 -> 4.1447291 | J80: =$C80*J63 -> 1.9032818 | K80: =$C80*K63 -> 0.39409496 | L80: =$C80*L63 -> 0 | M80: =$C80*M63 -> 0 | ... P80: =$C80*P63 -> 0
B81: 42004 | C81: =C80 -> 0.055 | G81: =$C81*G64 -> 4.9225 | H81: =$C81*H64 -> 8.695775 | I81: =$C81*I64 -> 6.4088173 | J81: =$C81*J64 -> 4.1447291 | K81: =$C81*K64 -> 1.9032818 | L81: =$C81*L64 -> 0.39409496 | M81: =$C81*M64 -> 0 | N81: =$C81*N64 -> 0 | ... P81: =$C81*P64 -> 0
B82: 42369 | C82: =C81 -> 0.055 | H82: =$C82*H65 -> 4.9225 | I82: =$C82*I65 -> 8.695775 | J82: =$C82*J65 -> 6.4088173 | K82: =$C82*K65 -> 4.1447291 | L82: =$C82*L65 -> 1.9032818 | M82: =$C82*M65 -> 0.39409496 | N82: =$C82*N65 -> 0 | O82: =$C82*O65 -> 0 | P82: =$C82*P65 -> 0
B83: 42735 | C83: =C82 -> 0.055 | I83: =$C83*I66 -> 4.9225 | J83: =$C83*J66 -> 8.695775 | K83: =$C83*K66 -> 6.4088173 | L83: =$C83*L66 -> 4.1447291 | M83: =$C83*M66 -> 1.9032818 | N83: =$C83*N66 -> 0.39409496 | O83: =$C83*O66 -> 0 | P83: =$C83*P66 -> 0
B84: 43100 | C84: =C83 -> 0.055 | J84: =$C84*J67 -> 4.9225 | K84: =$C84*K67 -> 8.695775 | L84: =$C84*L67 -> 6.4088173 | M84: =$C84*M67 -> 4.1447291 | N84: =$C84*N67 -> 1.9032818 | O84: =$C84*O67 -> 0.39409496 | P84: =$C84*P67 -> 0
B85: 43465 | C85: =C84 -> 0.055 | K85: =$C85*K68 -> 4.9225 | L85: =$C85*L68 -> 8.695775 | M85: =$C85*M68 -> 6.4088173 | N85: =$C85*N68 -> 4.1447291 | O85: =$C85*O68 -> 1.9032818 | P85: =$C85*P68 -> 0.39409496
B86: 43830 | C86: =C85 -> 0.055 | L86: =$C86*L69 -> 4.9225 | M86: =$C86*M69 -> 8.695775 | N86: =$C86*N69 -> 6.4088173 | O86: =$C86*O69 -> 4.1447291 | P86: =$C86*P69 -> 1.9032818
B87: 44196 | C87: =C86 -> 0.055 | M87: =$C87*M70 -> 4.9225 | N87: =$C87*N70 -> 8.695775 | O87: =$C87*O70 -> 6.4088173 | P87: =$C87*P70 -> 4.1447291
B88: 44561 | C88: =C87 -> 0.055 | N88: =$C88*N71 -> 4.9225 | O88: =$C88*O71 -> 8.695775 | P88: =$C88*P71 -> 6.4088173
B89: 44926 | C89: =C88 -> 0.055 | O89: =$C89*O72 -> 4.9225 | P89: =$C89*P72 -> 8.695775
B90: 45291 | C90: =C89 -> 0.055 | P90: =$C90*P73 -> 4.9225
B91: Total Interest Income | E91: =SUM(E79:E90) -> 4.9225 | F91: =SUM(F79:F90) -> 13.618275 | G91: =SUM(G79:G90) -> 20.027092 | H91: =SUM(H79:H90) -> 24.171821 | I91: =SUM(I79:I90) -> 26.075103 | J91: =SUM(J79:J90) -> 26.469198 | K91: =SUM(K79:K90) -> 26.469198 | L91: =SUM(L79:L90) -> 26.469198 | ... P91: =SUM(P79:P90) -> 26.469198

Sheet pres output
B1: Standard Operating Model
B2: Presentation Outputs
A4: x | L4: x
C5: Projected | K5: CAGR/
B6: ($MM, unless noted) | C6: 2013 | D6: =C6+1 -> 2014 | E6: =D6+1 -> 2015 | F6: =E6+1 -> 2016 | G6: =F6+1 -> 2017 | H6: =G6+1 -> 2018 | K6: Change
B8: Summary Balance Sheet
B9: Cash and Equivalents | C9: =model!F284 -> 482.25063 | D9: =model!H284 -> 647.71195 | E9: =model!I284 -> 664.37669 | F9: =model!J284 -> 678.12151 | G9: =model!K284 -> 689.5712 | H9: =model!L284 -> 699.21956 | K9: =RATE(5,0,-C9,G9)*100 -> 7.4140924
B10: Loans, Net | C10: =model!F289 -> 1444.5025 | D10: =model!H289 -> 2081.774 | E10: =model!I289 -> 2138.3515 | F10: =model!J289 -> 2183.0477 | G10: =model!K289 -> 2218.3577 | H10: =model!L289 -> 2246.2525 | K10: =RATE(5,0,-C10,G10)*100 -> 8.9588858
B11: Total Assets | C11: =model!F294 -> 2028.7531 | D11: =model!H294 -> 2891.6568 | E11: =model!I294 -> 2967.0214 | F11: =model!J294 -> 3027.6273 | G11: =model!K294 -> 3076.5951 | H11: =model!L294 -> 3116.3907 | K11: =RATE(5,0,-C11,G11)*100 -> 8.6846543
B12: Deposits | C12: =model!F305 -> 1575 | D12: =model!H305 -> 2336.4375 | E12: =model!I305 -> 2423.2594 | F12: =model!J305 -> 2514.4223 | G12: =model!K305 -> 2610.1435 | H12: =model!L305 -> 2710.6506 | K12: =RATE(5,0,-C12,G12)*100 -> 10.630981
B13: Common Equity | C13: =model!F274 -> 168.38745 | D13: =model!H274 -> 200.17396 | E13: =model!I274 -> 219.98828 | F13: =model!J274 -> 243.34383 | G13: =model!K274 -> 267.19715 | H13: =model!L274 -> 291.47773 | K13: =RATE(5,0,-C13,G13)*100 -> 9.6741862
B15: Summary Capitalization and Balance Sheet Metrics
B16: Tier 1 Ratio (%) | C16: =model!F319*100 -> 11.778022 | D16: =model!G319*100 -> 8.69485 | E16: =model!H319*100 -> 9.230191 | F16: =model!I319*100 -> 9.9178587 | G16: =model!J319*100 -> 10.784804 | H16: =model!K319*100 -> 11.684968 | K16: =H16-C16 -> -0.093054257
B17: Tier 1 Leverage (%) | C17: =model!F320*100 -> 8.3000465 | D17: =model!G320*100 -> 6.3400034 | E17: =model!H320*100 -> 6.7273186 | F17: =model!I320*100 -> 7.2252735 | G17: =model!J320*100 -> 7.8533099 | H17: =model!K320*100 -> 8.5049119 | K17: =H17-C17 -> 0.20486539
B18: Loans/Deposits (%) | C18: =C10/C12*100 -> 91.714444 | D18: =D10/D12*100 -> 89.100351 | E18: =E10/E12*100 -> 88.242781 | F18: =F10/F12*100 -> 86.821041 | G18: =G10/G12*100 -> 84.989874 | H18: =H10/H12*100 -> 82.867652 | K18: =H18-C18 -> -8.8467921
B20: Summary Income Statement and Performance Metrics
B21: Net Income | C21: =model!G252 -> 22.532122 | D21: =model!H252 -> 26.3702 | E21: =model!I252 -> 30.483566 | F21: =model!J252 -> 35.931609 | G21: =model!K252 -> 36.69743 | H21: =model!L252 -> 37.354736 | K21: =RATE(5,0,-C21,G21)*100 -> 10.246982
B22: Dividends | C22: =-(model!G270+model!G271) -> 7.8862426 | D22: =-(model!H270+model!H271) -> 9.22957 | E22: =-(model!I270+model!I271) -> 10.669248 | F22: =-(model!J270+model!J271) -> 12.576063 | G22: =-(model!K270+model!K271) -> 12.8441 | H22: =-(model!L270+model!L271) -> 13.074158 | K22: =RATE(5,0,-C22,G22)*100 -> 10.246982
B23: Net Interest Margin (%) | C23: =model!G311*100 -> 3.4538544 | D23: =model!H311*100 -> 3.4902087 | E23: =model!I311*100 -> 3.505303 | F23: =model!J311*100 -> 3.521112 | G23: =model!K311*100 -> 3.5376985 | H23: =model!L311*100 -> 3.5551107 | K23: =H23-C23 -> 0.10125635
B24: Fee Income Ratio (%) | C24: =model!G312*100 -> 20 | D24: =model!H312*100 -> 18.934197 | E24: =model!I312*100 -> 18.971039 | F24: =model!J312*100 -> 18.999893 | G24: =model!K312*100 -> 19.023058 | H24: =model!L312*100 -> 19.042101 | K24: =H24-C24 -> -0.95789913
B25: Efficiency Ratio (%) | C25: =model!G313*100 -> 60 | D25: =model!H313*100 -> 53.205509 | E25: =model!I313*100 -> 49.581771 | F25: =model!J313*100 -> 55.499519 | G25: =model!K313*100 -> 55.60376 | H25: =model!L313*100 -> 55.689454 | K25: =H25-C25 -> -4.3105461
B26: Return on Assets (%) | C26: =model!G314*100 -> 1.4677406 | D26: =model!H314*100 -> 1.1679475 | E26: =model!I314*100 -> 1.3171252 | F26: =model!J314*100 -> 1.5231082 | G26: =model!K314*100 -> 1.5326308 | H26: =model!L314*100 -> 1.5421169 | K26: =H26-C26 -> 0.074376292
B27: Return on Tangible Common Equity (%) | C27: =model!G316*100 -> 12.731211 | D27: =model!H316*100 -> 13.584207 | E27: =model!I316*100 -> 14.248767 | F27: =model!J316*100 -> 15.142244 | G27: =model!K316*100 -> 14.052395 | H27: =model!L316*100 -> 13.087283 | K27: =H27-C27 -> 0.35607209

Sheet chart output
B1: Standard Operating Model
B2: Presentation Outputs
B4: IRR Build-up:
B6: Base IRR | D6: 0 | E6: =F6-D6 -> 10.571286 | F6: =G6*100 -> 10.571286 | G6: =model!F376 -> 0.10571286
B7: Standalone Multiple Expansion | D7: =F6 -> 10.571286 | E7: =F7-D7 -> 2.7747047 | F7: =model!F378*100 -> 13.345991
B8: Standalone IRR | D8: 0 | E8: =F7 -> 13.345991
B9: Target Acquisition | D9: =E8 -> 13.345991 | E9: =F9-D9 -> 7.2391939 | F9: =model!M378*100 -> 20.585185
B10: Pro Forma IRR | D10: 0 | E10: =F9 -> 20.585185
